malloc_tag/libs/mtag_graphviz_utils.py
malloc_tag/libs/mtag_node.py
malloc_tag/libs/mtag_snapshot.py
malloc_tag/libs/mtag_tree.py
malloctag_tools-1.5.4.dist-info/METADATA
malloctag_tools-1.5.4.dist-info/WHEEL
malloctag_tools-1.5.4.dist-info/entry_points.txt
malloctag_tools-1.5.4.dist-info/RECORD
