Metadata-Version: 2.4
Name: malloctag-tools
Version: 1.5.4
Summary: Utility to postprocess malloc-tag JSON snapshots
Project-URL: Homepage, https://github.com/f18m/malloc-tag
Project-URL: Bug Tracker, https://github.com/f18m/malloc-tag/issues
Author-email: Francesco Montorsi <francesco.montorsi@gmail.com>
Classifier: License :: OSI Approved :: MIT License
Classifier: Operating System :: OS Independent
Classifier: Programming Language :: Python :: 3
Requires-Python: >=3.6
Requires-Dist: graphviz>=0.19.1
